<anim ver="netanim-3.109" filetype="animation" >
<node id="0" sysId="0" locX="10.1642394" locY="48.3667669" />
<node id="1" sysId="0" locX="33.19520939" locY="60.08707478" />
<node id="2" sysId="0" locX="24.07839501" locY="7.499407944" />
<node id="3" sysId="0" locX="24.46569223" locY="1.146132508" />
<node id="4" sysId="0" locX="63.36732353" locY="1.714670648" />
<node id="5" sysId="0" locX="41.49032075" locY="14.02157082" />
<node id="6" sysId="0" locX="96.68023768" locY="72.74518826" />
<node id="7" sysId="0" locX="97.48764706" locY="73.84707023" />
<node id="8" sysId="0" locX="58.73048229" locY="68.15031079" />
<node id="9" sysId="0" locX="28.74885159" locY="48.13048011" />
<node id="10" sysId="0" locX="66.00376897" locY="18.74185286" />
<node id="11" sysId="0" locX="57.54585768" locY="42.1699142" />
<node id="12" sysId="0" locX="22.38854173" locY="71.71712914" />
<node id="13" sysId="0" locX="97.25649346" locY="35.41211601" />
<node id="14" sysId="0" locX="48.05783552" locY="25.89872582" />
<node id="15" sysId="0" locX="44.49533791" locY="48.2410526" />
<node id="16" sysId="0" locX="90.91499984" locY="56.421992" />
<node id="17" sysId="0" locX="76.3848454" locY="75.48442357" />
<node id="18" sysId="0" locX="98.67443063" locY="64.78404784" />
<node id="19" sysId="0" locX="75.46808924" locY="2.464893649" />
<node id="20" sysId="0" locX="55.10605463" locY="99.13827582" />
<node id="21" sysId="0" locX="90.6117607" locY="67.60686495" />
<node id="22" sysId="0" locX="2.144348097" locY="97.35260819" />
<node id="23" sysId="0" locX="91.41220989" locY="50.38693526" />
<node id="24" sysId="0" locX="29.18300628" locY="45.81198539" />
<node id="25" sysId="0" locX="62.1055808" locY="1.052445457" />
<node id="26" sysId="0" locX="74.17789237" locY="1.755997367" />
<node id="27" sysId="0" locX="10.43864141" locY="80.63488155" />
<node id="28" sysId="0" locX="51.39449499" locY="5.770233506" />
<node id="29" sysId="0" locX="13.82036658" locY="64.62626044" />
<node id="30" sysId="0" locX="67.31340054" locY="6.050083753" />
<node id="31" sysId="0" locX="56.69034538" locY="99.95145635" />
<node id="32" sysId="0" locX="73.80211531" locY="41.86557534" />
<node id="33" sysId="0" locX="17.97525495" locY="39.65635825" />
<node id="34" sysId="0" locX="90.35211415" locY="54.93776627" />
<node id="35" sysId="0" locX="86.49439367" locY="73.80534204" />
<node id="36" sysId="0" locX="45.821621" locY="98.61508906" />
<node id="37" sysId="0" locX="37.86235526" locY="48.89842588" />
<node id="38" sysId="0" locX="69.92224172" locY="66.21381486" />
<node id="39" sysId="0" locX="12.35696712" locY="78.05725318" />
<node id="40" sysId="0" locX="57.73036757" locY="6.692920204" />
<node id="41" sysId="0" locX="71.3170562" locY="5.369530343" />
<node id="42" sysId="0" locX="85.30886237" locY="41.81607612" />
<node id="43" sysId="0" locX="71.17406302" locY="83.19991043" />
<node id="44" sysId="0" locX="58.95625406" locY="65.91093079" />
<node id="45" sysId="0" locX="98.31100515" locY="21.11908037" />
<node id="46" sysId="0" locX="16.42984318" locY="55.81894042" />
<node id="47" sysId="0" locX="40.83813701" locY="25.51406999" />
<node id="48" sysId="0" locX="96.10221539" locY="11.13959579" />
<node id="49" sysId="0" locX="1.031878175" locY="56.0615065" />
<nu p="c" t="0" id="0" r="255" g="0" b="0" />
<nu p="c" t="0" id="1" r="255" g="0" b="0" />
<nu p="c" t="0" id="2" r="255" g="0" b="0" />
<nu p="c" t="0" id="3" r="255" g="0" b="0" />
<nu p="c" t="0" id="4" r="255" g="0" b="0" />
<nu p="c" t="0" id="5" r="255" g="0" b="0" />
<nu p="c" t="0" id="6" r="255" g="0" b="0" />
<nu p="c" t="0" id="7" r="255" g="0" b="0" />
<nu p="c" t="0" id="8" r="255" g="0" b="0" />
<nu p="c" t="0" id="9" r="255" g="0" b="0" />
<nu p="c" t="0" id="10" r="255" g="0" b="0" />
<nu p="c" t="0" id="11" r="255" g="0" b="0" />
<nu p="c" t="0" id="12" r="255" g="0" b="0" />
<nu p="c" t="0" id="13" r="255" g="0" b="0" />
<nu p="c" t="0" id="14" r="255" g="0" b="0" />
<nu p="c" t="0" id="15" r="255" g="0" b="0" />
<nu p="c" t="0" id="16" r="255" g="0" b="0" />
<nu p="c" t="0" id="17" r="255" g="0" b="0" />
<nu p="c" t="0" id="18" r="255" g="0" b="0" />
<nu p="c" t="0" id="19" r="255" g="0" b="0" />
<nu p="c" t="0" id="20" r="255" g="0" b="0" />
<nu p="c" t="0" id="21" r="255" g="0" b="0" />
<nu p="c" t="0" id="22" r="255" g="0" b="0" />
<nu p="c" t="0" id="23" r="255" g="0" b="0" />
<nu p="c" t="0" id="24" r="255" g="0" b="0" />
<nu p="c" t="0" id="25" r="255" g="0" b="0" />
<nu p="c" t="0" id="26" r="255" g="0" b="0" />
<nu p="c" t="0" id="27" r="255" g="0" b="0" />
<nu p="c" t="0" id="28" r="255" g="0" b="0" />
<nu p="c" t="0" id="29" r="255" g="0" b="0" />
<nu p="c" t="0" id="30" r="255" g="0" b="0" />
<nu p="c" t="0" id="31" r="255" g="0" b="0" />
<nu p="c" t="0" id="32" r="255" g="0" b="0" />
<nu p="c" t="0" id="33" r="255" g="0" b="0" />
<nu p="c" t="0" id="34" r="255" g="0" b="0" />
<nu p="c" t="0" id="35" r="255" g="0" b="0" />
<nu p="c" t="0" id="36" r="255" g="0" b="0" />
<nu p="c" t="0" id="37" r="255" g="0" b="0" />
<nu p="c" t="0" id="38" r="255" g="0" b="0" />
<nu p="c" t="0" id="39" r="255" g="0" b="0" />
<nu p="c" t="0" id="40" r="255" g="0" b="0" />
<nu p="c" t="0" id="41" r="255" g="0" b="0" />
<nu p="c" t="0" id="42" r="255" g="0" b="0" />
<nu p="c" t="0" id="43" r="255" g="0" b="0" />
<nu p="c" t="0" id="44" r="255" g="0" b="0" />
<nu p="c" t="0" id="45" r="255" g="0" b="0" />
<nu p="c" t="0" id="46" r="255" g="0" b="0" />
<nu p="c" t="0" id="47" r="255" g="0" b="0" />
<nu p="c" t="0" id="48" r="255" g="0" b="0" />
<nu p="c" t="0" id="49" r="255" g="0" b="0" />
<nonp2plinkproperties id="0" ipAddress="127.0.0.1~00:00:00:00:00:00" channelType="Unknown channel" />
<link fromId="0" toId="36" fd="40.1.1.1~00:00:00:00:00:01" td="40.1.1.2~00:00:00:00:00:02" ld="" />
<link fromId="0" toId="5" fd="40.1.2.1~00:00:00:00:00:03" td="40.1.2.2~00:00:00:00:00:04" ld="" />
<link fromId="0" toId="6" fd="40.1.3.1~00:00:00:00:00:05" td="40.1.3.2~00:00:00:00:00:06" ld="" />
<nonp2plinkproperties id="1" ipAddress="127.0.0.1~00:00:00:00:00:00" channelType="Unknown channel" />
<link fromId="1" toId="28" fd="40.1.4.1~00:00:00:00:00:07" td="40.1.4.2~00:00:00:00:00:08" ld="" />
<link fromId="1" toId="36" fd="40.1.5.1~00:00:00:00:00:09" td="40.1.5.2~00:00:00:00:00:0a" ld="" />
<link fromId="1" toId="19" fd="40.1.6.1~00:00:00:00:00:0b" td="40.1.6.2~00:00:00:00:00:0c" ld="" />
<nonp2plinkproperties id="2" ipAddress="127.0.0.1~00:00:00:00:00:00" channelType="Unknown channel" />
<link fromId="2" toId="45" fd="40.1.7.1~00:00:00:00:00:0d" td="40.1.7.2~00:00:00:00:00:0e" ld="" />
<link fromId="2" toId="25" fd="40.1.8.1~00:00:00:00:00:0f" td="40.1.8.2~00:00:00:00:00:10" ld="" />
<link fromId="2" toId="30" fd="40.1.9.1~00:00:00:00:00:11" td="40.1.9.2~00:00:00:00:00:12" ld="" />
<nonp2plinkproperties id="3" ipAddress="127.0.0.1~00:00:00:00:00:00" channelType="Unknown channel" />
<link fromId="3" toId="23" fd="40.1.10.1~00:00:00:00:00:13" td="40.1.10.2~00:00:00:00:00:14" ld="" />
<link fromId="3" toId="29" fd="40.1.11.1~00:00:00:00:00:15" td="40.1.11.2~00:00:00:00:00:16" ld="" />
<link fromId="3" toId="32" fd="40.1.12.1~00:00:00:00:00:17" td="40.1.12.2~00:00:00:00:00:18" ld="" />
<nonp2plinkproperties id="4" ipAddress="127.0.0.1~00:00:00:00:00:00" channelType="Unknown channel" />
<link fromId="4" toId="14" fd="40.1.13.1~00:00:00:00:00:19" td="40.1.13.2~00:00:00:00:00:1a" ld="" />
<link fromId="4" toId="29" fd="40.1.14.1~00:00:00:00:00:1b" td="40.1.14.2~00:00:00:00:00:1c" ld="" />
<link fromId="4" toId="37" fd="40.1.15.1~00:00:00:00:00:1d" td="40.1.15.2~00:00:00:00:00:1e" ld="" />
<nonp2plinkproperties id="5" ipAddress="127.0.0.1~00:00:00:00:00:00" channelType="Unknown channel" />
<link fromId="5" toId="21" fd="40.1.16.1~00:00:00:00:00:1f" td="40.1.16.2~00:00:00:00:00:20" ld="" />
<link fromId="5" toId="35" fd="40.1.17.1~00:00:00:00:00:21" td="40.1.17.2~00:00:00:00:00:22" ld="" />
<nonp2plinkproperties id="6" ipAddress="127.0.0.1~00:00:00:00:00:00" channelType="Unknown channel" />
<link fromId="6" toId="24" fd="40.1.18.1~00:00:00:00:00:23" td="40.1.18.2~00:00:00:00:00:24" ld="" />
<link fromId="6" toId="39" fd="40.1.19.1~00:00:00:00:00:25" td="40.1.19.2~00:00:00:00:00:26" ld="" />
<nonp2plinkproperties id="7" ipAddress="127.0.0.1~00:00:00:00:00:00" channelType="Unknown channel" />
<link fromId="7" toId="10" fd="40.1.20.1~00:00:00:00:00:27" td="40.1.20.2~00:00:00:00:00:28" ld="" />
<link fromId="7" toId="24" fd="40.1.21.1~00:00:00:00:00:29" td="40.1.21.2~00:00:00:00:00:2a" ld="" />
<link fromId="7" toId="30" fd="40.1.22.1~00:00:00:00:00:2b" td="40.1.22.2~00:00:00:00:00:2c" ld="" />
<nonp2plinkproperties id="8" ipAddress="127.0.0.1~00:00:00:00:00:00" channelType="Unknown channel" />
<link fromId="8" toId="36" fd="40.1.23.1~00:00:00:00:00:2d" td="40.1.23.2~00:00:00:00:00:2e" ld="" />
<link fromId="8" toId="35" fd="40.1.24.1~00:00:00:00:00:2f" td="40.1.24.2~00:00:00:00:00:30" ld="" />
<link fromId="8" toId="40" fd="40.1.25.1~00:00:00:00:00:31" td="40.1.25.2~00:00:00:00:00:32" ld="" />
<nonp2plinkproperties id="9" ipAddress="127.0.0.1~00:00:00:00:00:00" channelType="Unknown channel" />
<link fromId="9" toId="29" fd="40.1.26.1~00:00:00:00:00:33" td="40.1.26.2~00:00:00:00:00:34" ld="" />
<link fromId="9" toId="32" fd="40.1.27.1~00:00:00:00:00:35" td="40.1.27.2~00:00:00:00:00:36" ld="" />
<link fromId="9" toId="12" fd="40.1.28.1~00:00:00:00:00:37" td="40.1.28.2~00:00:00:00:00:38" ld="" />
<nonp2plinkproperties id="10" ipAddress="127.0.0.1~00:00:00:00:00:00" channelType="Unknown channel" />
<link fromId="10" toId="15" fd="40.1.29.1~00:00:00:00:00:39" td="40.1.29.2~00:00:00:00:00:3a" ld="" />
<link fromId="10" toId="27" fd="40.1.30.1~00:00:00:00:00:3b" td="40.1.30.2~00:00:00:00:00:3c" ld="" />
<nonp2plinkproperties id="11" ipAddress="127.0.0.1~00:00:00:00:00:00" channelType="Unknown channel" />
<link fromId="11" toId="20" fd="40.1.31.1~00:00:00:00:00:3d" td="40.1.31.2~00:00:00:00:00:3e" ld="" />
<link fromId="11" toId="31" fd="40.1.32.1~00:00:00:00:00:3f" td="40.1.32.2~00:00:00:00:00:40" ld="" />
<link fromId="11" toId="43" fd="40.1.33.1~00:00:00:00:00:41" td="40.1.33.2~00:00:00:00:00:42" ld="" />
<nonp2plinkproperties id="12" ipAddress="127.0.0.1~00:00:00:00:00:00" channelType="Unknown channel" />
<link fromId="12" toId="20" fd="40.1.34.1~00:00:00:00:00:43" td="40.1.34.2~00:00:00:00:00:44" ld="" />
<link fromId="12" toId="47" fd="40.1.35.1~00:00:00:00:00:45" td="40.1.35.2~00:00:00:00:00:46" ld="" />
<nonp2plinkproperties id="13" ipAddress="127.0.0.1~00:00:00:00:00:00" channelType="Unknown channel" />
<link fromId="13" toId="27" fd="40.1.36.1~00:00:00:00:00:47" td="40.1.36.2~00:00:00:00:00:48" ld="" />
<link fromId="13" toId="17" fd="40.1.37.1~00:00:00:00:00:49" td="40.1.37.2~00:00:00:00:00:4a" ld="" />
<link fromId="13" toId="37" fd="40.1.38.1~00:00:00:00:00:4b" td="40.1.38.2~00:00:00:00:00:4c" ld="" />
<nonp2plinkproperties id="14" ipAddress="127.0.0.1~00:00:00:00:00:00" channelType="Unknown channel" />
<link fromId="14" toId="45" fd="40.1.39.1~00:00:00:00:00:4d" td="40.1.39.2~00:00:00:00:00:4e" ld="" />
<link fromId="14" toId="32" fd="40.1.40.1~00:00:00:00:00:4f" td="40.1.40.2~00:00:00:00:00:50" ld="" />
<nonp2plinkproperties id="15" ipAddress="127.0.0.1~00:00:00:00:00:00" channelType="Unknown channel" />
<link fromId="15" toId="39" fd="40.1.41.1~00:00:00:00:00:51" td="40.1.41.2~00:00:00:00:00:52" ld="" />
<link fromId="15" toId="28" fd="40.1.42.1~00:00:00:00:00:53" td="40.1.42.2~00:00:00:00:00:54" ld="" />
<nonp2plinkproperties id="16" ipAddress="127.0.0.1~00:00:00:00:00:00" channelType="Unknown channel" />
<link fromId="16" toId="28" fd="40.1.43.1~00:00:00:00:00:55" td="40.1.43.2~00:00:00:00:00:56" ld="" />
<link fromId="16" toId="18" fd="40.1.44.1~00:00:00:00:00:57" td="40.1.44.2~00:00:00:00:00:58" ld="" />
<link fromId="16" toId="42" fd="40.1.45.1~00:00:00:00:00:59" td="40.1.45.2~00:00:00:00:00:5a" ld="" />
<nonp2plinkproperties id="17" ipAddress="127.0.0.1~00:00:00:00:00:00" channelType="Unknown channel" />
<link fromId="17" toId="21" fd="40.1.46.1~00:00:00:00:00:5b" td="40.1.46.2~00:00:00:00:00:5c" ld="" />
<link fromId="17" toId="31" fd="40.1.47.1~00:00:00:00:00:5d" td="40.1.47.2~00:00:00:00:00:5e" ld="" />
<nonp2plinkproperties id="18" ipAddress="127.0.0.1~00:00:00:00:00:00" channelType="Unknown channel" />
<link fromId="18" toId="38" fd="40.1.48.1~00:00:00:00:00:5f" td="40.1.48.2~00:00:00:00:00:60" ld="" />
<link fromId="18" toId="43" fd="40.1.49.1~00:00:00:00:00:61" td="40.1.49.2~00:00:00:00:00:62" ld="" />
<nonp2plinkproperties id="19" ipAddress="127.0.0.1~00:00:00:00:00:00" channelType="Unknown channel" />
<link fromId="19" toId="42" fd="40.1.50.1~00:00:00:00:00:63" td="40.1.50.2~00:00:00:00:00:64" ld="" />
<link fromId="19" toId="37" fd="40.1.51.1~00:00:00:00:00:65" td="40.1.51.2~00:00:00:00:00:66" ld="" />
<nonp2plinkproperties id="20" ipAddress="127.0.0.1~00:00:00:00:00:00" channelType="Unknown channel" />
<link fromId="20" toId="27" fd="40.1.52.1~00:00:00:00:00:67" td="40.1.52.2~00:00:00:00:00:68" ld="" />
<nonp2plinkproperties id="21" ipAddress="127.0.0.1~00:00:00:00:00:00" channelType="Unknown channel" />
<link fromId="21" toId="30" fd="40.1.53.1~00:00:00:00:00:69" td="40.1.53.2~00:00:00:00:00:6a" ld="" />
<nonp2plinkproperties id="22" ipAddress="127.0.0.1~00:00:00:00:00:00" channelType="Unknown channel" />
<link fromId="22" toId="47" fd="40.1.54.1~00:00:00:00:00:6b" td="40.1.54.2~00:00:00:00:00:6c" ld="" />
<link fromId="22" toId="49" fd="40.1.55.1~00:00:00:00:00:6d" td="40.1.55.2~00:00:00:00:00:6e" ld="" />
<link fromId="22" toId="48" fd="40.1.56.1~00:00:00:00:00:6f" td="40.1.56.2~00:00:00:00:00:70" ld="" />
<nonp2plinkproperties id="23" ipAddress="127.0.0.1~00:00:00:00:00:00" channelType="Unknown channel" />
<link fromId="23" toId="49" fd="40.1.57.1~00:00:00:00:00:71" td="40.1.57.2~00:00:00:00:00:72" ld="" />
<link fromId="23" toId="44" fd="40.1.58.1~00:00:00:00:00:73" td="40.1.58.2~00:00:00:00:00:74" ld="" />
<nonp2plinkproperties id="24" ipAddress="127.0.0.1~00:00:00:00:00:00" channelType="Unknown channel" />
<link fromId="24" toId="48" fd="40.1.59.1~00:00:00:00:00:75" td="40.1.59.2~00:00:00:00:00:76" ld="" />
<nonp2plinkproperties id="25" ipAddress="127.0.0.1~00:00:00:00:00:00" channelType="Unknown channel" />
<link fromId="25" toId="41" fd="40.1.60.1~00:00:00:00:00:77" td="40.1.60.2~00:00:00:00:00:78" ld="" />
<link fromId="25" toId="42" fd="40.1.61.1~00:00:00:00:00:79" td="40.1.61.2~00:00:00:00:00:7a" ld="" />
<nonp2plinkproperties id="26" ipAddress="127.0.0.1~00:00:00:00:00:00" channelType="Unknown channel" />
<link fromId="26" toId="41" fd="40.1.62.1~00:00:00:00:00:7b" td="40.1.62.2~00:00:00:00:00:7c" ld="" />
<link fromId="26" toId="40" fd="40.1.63.1~00:00:00:00:00:7d" td="40.1.63.2~00:00:00:00:00:7e" ld="" />
<link fromId="26" toId="49" fd="40.1.64.1~00:00:00:00:00:7f" td="40.1.64.2~00:00:00:00:00:80" ld="" />
<nonp2plinkproperties id="27" ipAddress="127.0.0.1~00:00:00:00:00:00" channelType="Unknown channel" />
<nonp2plinkproperties id="28" ipAddress="127.0.0.1~00:00:00:00:00:00" channelType="Unknown channel" />
<nonp2plinkproperties id="29" ipAddress="127.0.0.1~00:00:00:00:00:00" channelType="Unknown channel" />
<nonp2plinkproperties id="30" ipAddress="127.0.0.1~00:00:00:00:00:00" channelType="Unknown channel" />
<nonp2plinkproperties id="31" ipAddress="127.0.0.1~00:00:00:00:00:00" channelType="Unknown channel" />
<link fromId="31" toId="43" fd="40.1.65.1~00:00:00:00:00:81" td="40.1.65.2~00:00:00:00:00:82" ld="" />
<nonp2plinkproperties id="32" ipAddress="127.0.0.1~00:00:00:00:00:00" channelType="Unknown channel" />
<nonp2plinkproperties id="33" ipAddress="127.0.0.1~00:00:00:00:00:00" channelType="Unknown channel" />
<link fromId="33" toId="48" fd="40.1.66.1~00:00:00:00:00:83" td="40.1.66.2~00:00:00:00:00:84" ld="" />
<link fromId="33" toId="44" fd="40.1.67.1~00:00:00:00:00:85" td="40.1.67.2~00:00:00:00:00:86" ld="" />
<link fromId="33" toId="41" fd="40.1.68.1~00:00:00:00:00:87" td="40.1.68.2~00:00:00:00:00:88" ld="" />
<nonp2plinkproperties id="34" ipAddress="127.0.0.1~00:00:00:00:00:00" channelType="Unknown channel" />
<link fromId="34" toId="40" fd="40.1.69.1~00:00:00:00:00:89" td="40.1.69.2~00:00:00:00:00:8a" ld="" />
<link fromId="34" toId="46" fd="40.1.70.1~00:00:00:00:00:8b" td="40.1.70.2~00:00:00:00:00:8c" ld="" />
<link fromId="34" toId="38" fd="40.1.71.1~00:00:00:00:00:8d" td="40.1.71.2~00:00:00:00:00:8e" ld="" />
<nonp2plinkproperties id="35" ipAddress="127.0.0.1~00:00:00:00:00:00" channelType="Unknown channel" />
<link fromId="35" toId="38" fd="40.1.72.1~00:00:00:00:00:8f" td="40.1.72.2~00:00:00:00:00:90" ld="" />
<nonp2plinkproperties id="36" ipAddress="127.0.0.1~00:00:00:00:00:00" channelType="Unknown channel" />
<nonp2plinkproperties id="37" ipAddress="127.0.0.1~00:00:00:00:00:00" channelType="Unknown channel" />
<nonp2plinkproperties id="38" ipAddress="127.0.0.1~00:00:00:00:00:00" channelType="Unknown channel" />
<nonp2plinkproperties id="39" ipAddress="127.0.0.1~00:00:00:00:00:00" channelType="Unknown channel" />
<link fromId="39" toId="46" fd="40.1.73.1~00:00:00:00:00:91" td="40.1.73.2~00:00:00:00:00:92" ld="" />
<nonp2plinkproperties id="40" ipAddress="127.0.0.1~00:00:00:00:00:00" channelType="Unknown channel" />
<nonp2plinkproperties id="41" ipAddress="127.0.0.1~00:00:00:00:00:00" channelType="Unknown channel" />
<nonp2plinkproperties id="42" ipAddress="127.0.0.1~00:00:00:00:00:00" channelType="Unknown channel" />
<nonp2plinkproperties id="43" ipAddress="127.0.0.1~00:00:00:00:00:00" channelType="Unknown channel" />
<nonp2plinkproperties id="44" ipAddress="127.0.0.1~00:00:00:00:00:00" channelType="Unknown channel" />
<link fromId="44" toId="47" fd="40.1.74.1~00:00:00:00:00:93" td="40.1.74.2~00:00:00:00:00:94" ld="" />
<nonp2plinkproperties id="45" ipAddress="127.0.0.1~00:00:00:00:00:00" channelType="Unknown channel" />
<link fromId="45" toId="46" fd="40.1.75.1~00:00:00:00:00:95" td="40.1.75.2~00:00:00:00:00:96" ld="" />
<nonp2plinkproperties id="46" ipAddress="127.0.0.1~00:00:00:00:00:00" channelType="Unknown channel" />
<nonp2plinkproperties id="47" ipAddress="127.0.0.1~00:00:00:00:00:00" channelType="Unknown channel" />
<nonp2plinkproperties id="48" ipAddress="127.0.0.1~00:00:00:00:00:00" channelType="Unknown channel" />
<nonp2plinkproperties id="49" ipAddress="127.0.0.1~00:00:00:00:00:00" channelType="Unknown channel" />
<ip n="0" >
<address >127.0.0.1</address>

<address >40.1.1.1</address>

<address >40.1.2.1</address>

<address >40.1.3.1</address>

</ip>
<ip n="0" >
<address >127.0.0.1</address>

<address >40.1.1.1</address>

<address >40.1.2.1</address>

<address >40.1.3.1</address>

</ip>
<ip n="0" >
<address >127.0.0.1</address>

<address >40.1.1.1</address>

<address >40.1.2.1</address>

<address >40.1.3.1</address>

</ip>
<ip n="0" >
<address >127.0.0.1</address>

<address >40.1.1.1</address>

<address >40.1.2.1</address>

<address >40.1.3.1</address>

</ip>
<ip n="1" >
<address >127.0.0.1</address>

<address >40.1.4.1</address>

<address >40.1.5.1</address>

<address >40.1.6.1</address>

</ip>
<ip n="1" >
<address >127.0.0.1</address>

<address >40.1.4.1</address>

<address >40.1.5.1</address>

<address >40.1.6.1</address>

</ip>
<ip n="1" >
<address >127.0.0.1</address>

<address >40.1.4.1</address>

<address >40.1.5.1</address>

<address >40.1.6.1</address>

</ip>
<ip n="1" >
<address >127.0.0.1</address>

<address >40.1.4.1</address>

<address >40.1.5.1</address>

<address >40.1.6.1</address>

</ip>
<ip n="2" >
<address >127.0.0.1</address>

<address >40.1.7.1</address>

<address >40.1.8.1</address>

<address >40.1.9.1</address>

</ip>
<ip n="2" >
<address >127.0.0.1</address>

<address >40.1.7.1</address>

<address >40.1.8.1</address>

<address >40.1.9.1</address>

</ip>
<ip n="2" >
<address >127.0.0.1</address>

<address >40.1.7.1</address>

<address >40.1.8.1</address>

<address >40.1.9.1</address>

</ip>
<ip n="2" >
<address >127.0.0.1</address>

<address >40.1.7.1</address>

<address >40.1.8.1</address>

<address >40.1.9.1</address>

</ip>
<ip n="3" >
<address >127.0.0.1</address>

<address >40.1.10.1</address>

<address >40.1.11.1</address>

<address >40.1.12.1</address>

</ip>
<ip n="3" >
<address >127.0.0.1</address>

<address >40.1.10.1</address>

<address >40.1.11.1</address>

<address >40.1.12.1</address>

</ip>
<ip n="3" >
<address >127.0.0.1</address>

<address >40.1.10.1</address>

<address >40.1.11.1</address>

<address >40.1.12.1</address>

</ip>
<ip n="3" >
<address >127.0.0.1</address>

<address >40.1.10.1</address>

<address >40.1.11.1</address>

<address >40.1.12.1</address>

</ip>
<ip n="4" >
<address >127.0.0.1</address>

<address >40.1.13.1</address>

<address >40.1.14.1</address>

<address >40.1.15.1</address>

</ip>
<ip n="4" >
<address >127.0.0.1</address>

<address >40.1.13.1</address>

<address >40.1.14.1</address>

<address >40.1.15.1</address>

</ip>
<ip n="4" >
<address >127.0.0.1</address>

<address >40.1.13.1</address>

<address >40.1.14.1</address>

<address >40.1.15.1</address>

</ip>
<ip n="4" >
<address >127.0.0.1</address>

<address >40.1.13.1</address>

<address >40.1.14.1</address>

<address >40.1.15.1</address>

</ip>
<ip n="5" >
<address >40.1.2.2</address>

<address >127.0.0.1</address>

<address >40.1.16.1</address>

<address >40.1.17.1</address>

</ip>
<ip n="5" >
<address >40.1.2.2</address>

<address >127.0.0.1</address>

<address >40.1.16.1</address>

<address >40.1.17.1</address>

</ip>
<ip n="5" >
<address >40.1.2.2</address>

<address >127.0.0.1</address>

<address >40.1.16.1</address>

<address >40.1.17.1</address>

</ip>
<ip n="5" >
<address >40.1.2.2</address>

<address >127.0.0.1</address>

<address >40.1.16.1</address>

<address >40.1.17.1</address>

</ip>
<ip n="6" >
<address >40.1.3.2</address>

<address >127.0.0.1</address>

<address >40.1.18.1</address>

<address >40.1.19.1</address>

</ip>
<ip n="6" >
<address >40.1.3.2</address>

<address >127.0.0.1</address>

<address >40.1.18.1</address>

<address >40.1.19.1</address>

</ip>
<ip n="6" >
<address >40.1.3.2</address>

<address >127.0.0.1</address>

<address >40.1.18.1</address>

<address >40.1.19.1</address>

</ip>
<ip n="6" >
<address >40.1.3.2</address>

<address >127.0.0.1</address>

<address >40.1.18.1</address>

<address >40.1.19.1</address>

</ip>
<ip n="7" >
<address >127.0.0.1</address>

<address >40.1.20.1</address>

<address >40.1.21.1</address>

<address >40.1.22.1</address>

</ip>
<ip n="7" >
<address >127.0.0.1</address>

<address >40.1.20.1</address>

<address >40.1.21.1</address>

<address >40.1.22.1</address>

</ip>
<ip n="7" >
<address >127.0.0.1</address>

<address >40.1.20.1</address>

<address >40.1.21.1</address>

<address >40.1.22.1</address>

</ip>
<ip n="7" >
<address >127.0.0.1</address>

<address >40.1.20.1</address>

<address >40.1.21.1</address>

<address >40.1.22.1</address>

</ip>
<ip n="8" >
<address >127.0.0.1</address>

<address >40.1.23.1</address>

<address >40.1.24.1</address>

<address >40.1.25.1</address>

</ip>
<ip n="8" >
<address >127.0.0.1</address>

<address >40.1.23.1</address>

<address >40.1.24.1</address>

<address >40.1.25.1</address>

</ip>
<ip n="8" >
<address >127.0.0.1</address>

<address >40.1.23.1</address>

<address >40.1.24.1</address>

<address >40.1.25.1</address>

</ip>
<ip n="8" >
<address >127.0.0.1</address>

<address >40.1.23.1</address>

<address >40.1.24.1</address>

<address >40.1.25.1</address>

</ip>
<ip n="9" >
<address >127.0.0.1</address>

<address >40.1.26.1</address>

<address >40.1.27.1</address>

<address >40.1.28.1</address>

</ip>
<ip n="9" >
<address >127.0.0.1</address>

<address >40.1.26.1</address>

<address >40.1.27.1</address>

<address >40.1.28.1</address>

</ip>
<ip n="9" >
<address >127.0.0.1</address>

<address >40.1.26.1</address>

<address >40.1.27.1</address>

<address >40.1.28.1</address>

</ip>
<ip n="9" >
<address >127.0.0.1</address>

<address >40.1.26.1</address>

<address >40.1.27.1</address>

<address >40.1.28.1</address>

</ip>
<ip n="10" >
<address >40.1.20.2</address>

<address >127.0.0.1</address>

<address >40.1.29.1</address>

<address >40.1.30.1</address>

</ip>
<ip n="10" >
<address >40.1.20.2</address>

<address >127.0.0.1</address>

<address >40.1.29.1</address>

<address >40.1.30.1</address>

</ip>
<ip n="10" >
<address >40.1.20.2</address>

<address >127.0.0.1</address>

<address >40.1.29.1</address>

<address >40.1.30.1</address>

</ip>
<ip n="10" >
<address >40.1.20.2</address>

<address >127.0.0.1</address>

<address >40.1.29.1</address>

<address >40.1.30.1</address>

</ip>
<ip n="11" >
<address >127.0.0.1</address>

<address >40.1.31.1</address>

<address >40.1.32.1</address>

<address >40.1.33.1</address>

</ip>
<ip n="11" >
<address >127.0.0.1</address>

<address >40.1.31.1</address>

<address >40.1.32.1</address>

<address >40.1.33.1</address>

</ip>
<ip n="11" >
<address >127.0.0.1</address>

<address >40.1.31.1</address>

<address >40.1.32.1</address>

<address >40.1.33.1</address>

</ip>
<ip n="11" >
<address >127.0.0.1</address>

<address >40.1.31.1</address>

<address >40.1.32.1</address>

<address >40.1.33.1</address>

</ip>
<ip n="12" >
<address >40.1.28.2</address>

<address >127.0.0.1</address>

<address >40.1.34.1</address>

<address >40.1.35.1</address>

</ip>
<ip n="12" >
<address >40.1.28.2</address>

<address >127.0.0.1</address>

<address >40.1.34.1</address>

<address >40.1.35.1</address>

</ip>
<ip n="12" >
<address >40.1.28.2</address>

<address >127.0.0.1</address>

<address >40.1.34.1</address>

<address >40.1.35.1</address>

</ip>
<ip n="12" >
<address >40.1.28.2</address>

<address >127.0.0.1</address>

<address >40.1.34.1</address>

<address >40.1.35.1</address>

</ip>
<ip n="13" >
<address >127.0.0.1</address>

<address >40.1.36.1</address>

<address >40.1.37.1</address>

<address >40.1.38.1</address>

</ip>
<ip n="13" >
<address >127.0.0.1</address>

<address >40.1.36.1</address>

<address >40.1.37.1</address>

<address >40.1.38.1</address>

</ip>
<ip n="13" >
<address >127.0.0.1</address>

<address >40.1.36.1</address>

<address >40.1.37.1</address>

<address >40.1.38.1</address>

</ip>
<ip n="13" >
<address >127.0.0.1</address>

<address >40.1.36.1</address>

<address >40.1.37.1</address>

<address >40.1.38.1</address>

</ip>
<ip n="14" >
<address >40.1.13.2</address>

<address >127.0.0.1</address>

<address >40.1.39.1</address>

<address >40.1.40.1</address>

</ip>
<ip n="14" >
<address >40.1.13.2</address>

<address >127.0.0.1</address>

<address >40.1.39.1</address>

<address >40.1.40.1</address>

</ip>
<ip n="14" >
<address >40.1.13.2</address>

<address >127.0.0.1</address>

<address >40.1.39.1</address>

<address >40.1.40.1</address>

</ip>
<ip n="14" >
<address >40.1.13.2</address>

<address >127.0.0.1</address>

<address >40.1.39.1</address>

<address >40.1.40.1</address>

</ip>
<ip n="15" >
<address >40.1.29.2</address>

<address >127.0.0.1</address>

<address >40.1.41.1</address>

<address >40.1.42.1</address>

</ip>
<ip n="15" >
<address >40.1.29.2</address>

<address >127.0.0.1</address>

<address >40.1.41.1</address>

<address >40.1.42.1</address>

</ip>
<ip n="15" >
<address >40.1.29.2</address>

<address >127.0.0.1</address>

<address >40.1.41.1</address>

<address >40.1.42.1</address>

</ip>
<ip n="15" >
<address >40.1.29.2</address>

<address >127.0.0.1</address>

<address >40.1.41.1</address>

<address >40.1.42.1</address>

</ip>
<ip n="16" >
<address >127.0.0.1</address>

<address >40.1.43.1</address>

<address >40.1.44.1</address>

<address >40.1.45.1</address>

</ip>
<ip n="16" >
<address >127.0.0.1</address>

<address >40.1.43.1</address>

<address >40.1.44.1</address>

<address >40.1.45.1</address>

</ip>
<ip n="16" >
<address >127.0.0.1</address>

<address >40.1.43.1</address>

<address >40.1.44.1</address>

<address >40.1.45.1</address>

</ip>
<ip n="16" >
<address >127.0.0.1</address>

<address >40.1.43.1</address>

<address >40.1.44.1</address>

<address >40.1.45.1</address>

</ip>
<ip n="17" >
<address >40.1.37.2</address>

<address >127.0.0.1</address>

<address >40.1.46.1</address>

<address >40.1.47.1</address>

</ip>
<ip n="17" >
<address >40.1.37.2</address>

<address >127.0.0.1</address>

<address >40.1.46.1</address>

<address >40.1.47.1</address>

</ip>
<ip n="17" >
<address >40.1.37.2</address>

<address >127.0.0.1</address>

<address >40.1.46.1</address>

<address >40.1.47.1</address>

</ip>
<ip n="17" >
<address >40.1.37.2</address>

<address >127.0.0.1</address>

<address >40.1.46.1</address>

<address >40.1.47.1</address>

</ip>
<ip n="18" >
<address >40.1.44.2</address>

<address >127.0.0.1</address>

<address >40.1.48.1</address>

<address >40.1.49.1</address>

</ip>
<ip n="18" >
<address >40.1.44.2</address>

<address >127.0.0.1</address>

<address >40.1.48.1</address>

<address >40.1.49.1</address>

</ip>
<ip n="18" >
<address >40.1.44.2</address>

<address >127.0.0.1</address>

<address >40.1.48.1</address>

<address >40.1.49.1</address>

</ip>
<ip n="18" >
<address >40.1.44.2</address>

<address >127.0.0.1</address>

<address >40.1.48.1</address>

<address >40.1.49.1</address>

</ip>
<ip n="19" >
<address >40.1.6.2</address>

<address >127.0.0.1</address>

<address >40.1.50.1</address>

<address >40.1.51.1</address>

</ip>
<ip n="19" >
<address >40.1.6.2</address>

<address >127.0.0.1</address>

<address >40.1.50.1</address>

<address >40.1.51.1</address>

</ip>
<ip n="19" >
<address >40.1.6.2</address>

<address >127.0.0.1</address>

<address >40.1.50.1</address>

<address >40.1.51.1</address>

</ip>
<ip n="19" >
<address >40.1.6.2</address>

<address >127.0.0.1</address>

<address >40.1.50.1</address>

<address >40.1.51.1</address>

</ip>
<ip n="20" >
<address >40.1.31.2</address>

<address >40.1.34.2</address>

<address >127.0.0.1</address>

<address >40.1.52.1</address>

</ip>
<ip n="20" >
<address >40.1.31.2</address>

<address >40.1.34.2</address>

<address >127.0.0.1</address>

<address >40.1.52.1</address>

</ip>
<ip n="20" >
<address >40.1.31.2</address>

<address >40.1.34.2</address>

<address >127.0.0.1</address>

<address >40.1.52.1</address>

</ip>
<ip n="20" >
<address >40.1.31.2</address>

<address >40.1.34.2</address>

<address >127.0.0.1</address>

<address >40.1.52.1</address>

</ip>
<ip n="21" >
<address >40.1.16.2</address>

<address >40.1.46.2</address>

<address >127.0.0.1</address>

<address >40.1.53.1</address>

</ip>
<ip n="21" >
<address >40.1.16.2</address>

<address >40.1.46.2</address>

<address >127.0.0.1</address>

<address >40.1.53.1</address>

</ip>
<ip n="21" >
<address >40.1.16.2</address>

<address >40.1.46.2</address>

<address >127.0.0.1</address>

<address >40.1.53.1</address>

</ip>
<ip n="21" >
<address >40.1.16.2</address>

<address >40.1.46.2</address>

<address >127.0.0.1</address>

<address >40.1.53.1</address>

</ip>
<ip n="22" >
<address >127.0.0.1</address>

<address >40.1.54.1</address>

<address >40.1.55.1</address>

<address >40.1.56.1</address>

</ip>
<ip n="22" >
<address >127.0.0.1</address>

<address >40.1.54.1</address>

<address >40.1.55.1</address>

<address >40.1.56.1</address>

</ip>
<ip n="22" >
<address >127.0.0.1</address>

<address >40.1.54.1</address>

<address >40.1.55.1</address>

<address >40.1.56.1</address>

</ip>
<ip n="22" >
<address >127.0.0.1</address>

<address >40.1.54.1</address>

<address >40.1.55.1</address>

<address >40.1.56.1</address>

</ip>
<ip n="23" >
<address >40.1.10.2</address>

<address >127.0.0.1</address>

<address >40.1.57.1</address>

<address >40.1.58.1</address>

</ip>
<ip n="23" >
<address >40.1.10.2</address>

<address >127.0.0.1</address>

<address >40.1.57.1</address>

<address >40.1.58.1</address>

</ip>
<ip n="23" >
<address >40.1.10.2</address>

<address >127.0.0.1</address>

<address >40.1.57.1</address>

<address >40.1.58.1</address>

</ip>
<ip n="23" >
<address >40.1.10.2</address>

<address >127.0.0.1</address>

<address >40.1.57.1</address>

<address >40.1.58.1</address>

</ip>
<ip n="24" >
<address >40.1.18.2</address>

<address >40.1.21.2</address>

<address >127.0.0.1</address>

<address >40.1.59.1</address>

</ip>
<ip n="24" >
<address >40.1.18.2</address>

<address >40.1.21.2</address>

<address >127.0.0.1</address>

<address >40.1.59.1</address>

</ip>
<ip n="24" >
<address >40.1.18.2</address>

<address >40.1.21.2</address>

<address >127.0.0.1</address>

<address >40.1.59.1</address>

</ip>
<ip n="24" >
<address >40.1.18.2</address>

<address >40.1.21.2</address>

<address >127.0.0.1</address>

<address >40.1.59.1</address>

</ip>
<ip n="25" >
<address >40.1.8.2</address>

<address >127.0.0.1</address>

<address >40.1.60.1</address>

<address >40.1.61.1</address>

</ip>
<ip n="25" >
<address >40.1.8.2</address>

<address >127.0.0.1</address>

<address >40.1.60.1</address>

<address >40.1.61.1</address>

</ip>
<ip n="25" >
<address >40.1.8.2</address>

<address >127.0.0.1</address>

<address >40.1.60.1</address>

<address >40.1.61.1</address>

</ip>
<ip n="25" >
<address >40.1.8.2</address>

<address >127.0.0.1</address>

<address >40.1.60.1</address>

<address >40.1.61.1</address>

</ip>
<ip n="26" >
<address >127.0.0.1</address>

<address >40.1.62.1</address>

<address >40.1.63.1</address>

<address >40.1.64.1</address>

</ip>
<ip n="26" >
<address >127.0.0.1</address>

<address >40.1.62.1</address>

<address >40.1.63.1</address>

<address >40.1.64.1</address>

</ip>
<ip n="26" >
<address >127.0.0.1</address>

<address >40.1.62.1</address>

<address >40.1.63.1</address>

<address >40.1.64.1</address>

</ip>
<ip n="26" >
<address >127.0.0.1</address>

<address >40.1.62.1</address>

<address >40.1.63.1</address>

<address >40.1.64.1</address>

</ip>
<ip n="27" >
<address >40.1.30.2</address>

<address >40.1.36.2</address>

<address >40.1.52.2</address>

<address >127.0.0.1</address>

</ip>
<ip n="27" >
<address >40.1.30.2</address>

<address >40.1.36.2</address>

<address >40.1.52.2</address>

<address >127.0.0.1</address>

</ip>
<ip n="27" >
<address >40.1.30.2</address>

<address >40.1.36.2</address>

<address >40.1.52.2</address>

<address >127.0.0.1</address>

</ip>
<ip n="27" >
<address >40.1.30.2</address>

<address >40.1.36.2</address>

<address >40.1.52.2</address>

<address >127.0.0.1</address>

</ip>
<ip n="28" >
<address >40.1.4.2</address>

<address >40.1.42.2</address>

<address >40.1.43.2</address>

<address >127.0.0.1</address>

</ip>
<ip n="28" >
<address >40.1.4.2</address>

<address >40.1.42.2</address>

<address >40.1.43.2</address>

<address >127.0.0.1</address>

</ip>
<ip n="28" >
<address >40.1.4.2</address>

<address >40.1.42.2</address>

<address >40.1.43.2</address>

<address >127.0.0.1</address>

</ip>
<ip n="28" >
<address >40.1.4.2</address>

<address >40.1.42.2</address>

<address >40.1.43.2</address>

<address >127.0.0.1</address>

</ip>
<ip n="29" >
<address >40.1.11.2</address>

<address >40.1.14.2</address>

<address >40.1.26.2</address>

<address >127.0.0.1</address>

</ip>
<ip n="29" >
<address >40.1.11.2</address>

<address >40.1.14.2</address>

<address >40.1.26.2</address>

<address >127.0.0.1</address>

</ip>
<ip n="29" >
<address >40.1.11.2</address>

<address >40.1.14.2</address>

<address >40.1.26.2</address>

<address >127.0.0.1</address>

</ip>
<ip n="29" >
<address >40.1.11.2</address>

<address >40.1.14.2</address>

<address >40.1.26.2</address>

<address >127.0.0.1</address>

</ip>
<ip n="30" >
<address >40.1.9.2</address>

<address >40.1.22.2</address>

<address >40.1.53.2</address>

<address >127.0.0.1</address>

</ip>
<ip n="30" >
<address >40.1.9.2</address>

<address >40.1.22.2</address>

<address >40.1.53.2</address>

<address >127.0.0.1</address>

</ip>
<ip n="30" >
<address >40.1.9.2</address>

<address >40.1.22.2</address>

<address >40.1.53.2</address>

<address >127.0.0.1</address>

</ip>
<ip n="30" >
<address >40.1.9.2</address>

<address >40.1.22.2</address>

<address >40.1.53.2</address>

<address >127.0.0.1</address>

</ip>
<ip n="31" >
<address >40.1.32.2</address>

<address >40.1.47.2</address>

<address >127.0.0.1</address>

<address >40.1.65.1</address>

</ip>
<ip n="31" >
<address >40.1.32.2</address>

<address >40.1.47.2</address>

<address >127.0.0.1</address>

<address >40.1.65.1</address>

</ip>
<ip n="31" >
<address >40.1.32.2</address>

<address >40.1.47.2</address>

<address >127.0.0.1</address>

<address >40.1.65.1</address>

</ip>
<ip n="31" >
<address >40.1.32.2</address>

<address >40.1.47.2</address>

<address >127.0.0.1</address>

<address >40.1.65.1</address>

</ip>
<ip n="32" >
<address >40.1.12.2</address>

<address >40.1.27.2</address>

<address >40.1.40.2</address>

<address >127.0.0.1</address>

</ip>
<ip n="32" >
<address >40.1.12.2</address>

<address >40.1.27.2</address>

<address >40.1.40.2</address>

<address >127.0.0.1</address>

</ip>
<ip n="32" >
<address >40.1.12.2</address>

<address >40.1.27.2</address>

<address >40.1.40.2</address>

<address >127.0.0.1</address>

</ip>
<ip n="32" >
<address >40.1.12.2</address>

<address >40.1.27.2</address>

<address >40.1.40.2</address>

<address >127.0.0.1</address>

</ip>
<ip n="33" >
<address >127.0.0.1</address>

<address >40.1.66.1</address>

<address >40.1.67.1</address>

<address >40.1.68.1</address>

</ip>
<ip n="33" >
<address >127.0.0.1</address>

<address >40.1.66.1</address>

<address >40.1.67.1</address>

<address >40.1.68.1</address>

</ip>
<ip n="33" >
<address >127.0.0.1</address>

<address >40.1.66.1</address>

<address >40.1.67.1</address>

<address >40.1.68.1</address>

</ip>
<ip n="33" >
<address >127.0.0.1</address>

<address >40.1.66.1</address>

<address >40.1.67.1</address>

<address >40.1.68.1</address>

</ip>
<ip n="34" >
<address >127.0.0.1</address>

<address >40.1.69.1</address>

<address >40.1.70.1</address>

<address >40.1.71.1</address>

</ip>
<ip n="34" >
<address >127.0.0.1</address>

<address >40.1.69.1</address>

<address >40.1.70.1</address>

<address >40.1.71.1</address>

</ip>
<ip n="34" >
<address >127.0.0.1</address>

<address >40.1.69.1</address>

<address >40.1.70.1</address>

<address >40.1.71.1</address>

</ip>
<ip n="34" >
<address >127.0.0.1</address>

<address >40.1.69.1</address>

<address >40.1.70.1</address>

<address >40.1.71.1</address>

</ip>
<ip n="35" >
<address >40.1.17.2</address>

<address >40.1.24.2</address>

<address >127.0.0.1</address>

<address >40.1.72.1</address>

</ip>
<ip n="35" >
<address >40.1.17.2</address>

<address >40.1.24.2</address>

<address >127.0.0.1</address>

<address >40.1.72.1</address>

</ip>
<ip n="35" >
<address >40.1.17.2</address>

<address >40.1.24.2</address>

<address >127.0.0.1</address>

<address >40.1.72.1</address>

</ip>
<ip n="35" >
<address >40.1.17.2</address>

<address >40.1.24.2</address>

<address >127.0.0.1</address>

<address >40.1.72.1</address>

</ip>
<ip n="36" >
<address >40.1.1.2</address>

<address >40.1.5.2</address>

<address >40.1.23.2</address>

<address >127.0.0.1</address>

</ip>
<ip n="36" >
<address >40.1.1.2</address>

<address >40.1.5.2</address>

<address >40.1.23.2</address>

<address >127.0.0.1</address>

</ip>
<ip n="36" >
<address >40.1.1.2</address>

<address >40.1.5.2</address>

<address >40.1.23.2</address>

<address >127.0.0.1</address>

</ip>
<ip n="36" >
<address >40.1.1.2</address>

<address >40.1.5.2</address>

<address >40.1.23.2</address>

<address >127.0.0.1</address>

</ip>
<ip n="37" >
<address >40.1.15.2</address>

<address >40.1.38.2</address>

<address >40.1.51.2</address>

<address >127.0.0.1</address>

</ip>
<ip n="37" >
<address >40.1.15.2</address>

<address >40.1.38.2</address>

<address >40.1.51.2</address>

<address >127.0.0.1</address>

</ip>
<ip n="37" >
<address >40.1.15.2</address>

<address >40.1.38.2</address>

<address >40.1.51.2</address>

<address >127.0.0.1</address>

</ip>
<ip n="37" >
<address >40.1.15.2</address>

<address >40.1.38.2</address>

<address >40.1.51.2</address>

<address >127.0.0.1</address>

</ip>
<ip n="38" >
<address >40.1.48.2</address>

<address >40.1.71.2</address>

<address >40.1.72.2</address>

<address >127.0.0.1</address>

</ip>
<ip n="38" >
<address >40.1.48.2</address>

<address >40.1.71.2</address>

<address >40.1.72.2</address>

<address >127.0.0.1</address>

</ip>
<ip n="38" >
<address >40.1.48.2</address>

<address >40.1.71.2</address>

<address >40.1.72.2</address>

<address >127.0.0.1</address>

</ip>
<ip n="38" >
<address >40.1.48.2</address>

<address >40.1.71.2</address>

<address >40.1.72.2</address>

<address >127.0.0.1</address>

</ip>
<ip n="39" >
<address >40.1.19.2</address>

<address >40.1.41.2</address>

<address >127.0.0.1</address>

<address >40.1.73.1</address>

</ip>
<ip n="39" >
<address >40.1.19.2</address>

<address >40.1.41.2</address>

<address >127.0.0.1</address>

<address >40.1.73.1</address>

</ip>
<ip n="39" >
<address >40.1.19.2</address>

<address >40.1.41.2</address>

<address >127.0.0.1</address>

<address >40.1.73.1</address>

</ip>
<ip n="39" >
<address >40.1.19.2</address>

<address >40.1.41.2</address>

<address >127.0.0.1</address>

<address >40.1.73.1</address>

</ip>
<ip n="40" >
<address >40.1.25.2</address>

<address >40.1.63.2</address>

<address >40.1.69.2</address>

<address >127.0.0.1</address>

</ip>
<ip n="40" >
<address >40.1.25.2</address>

<address >40.1.63.2</address>

<address >40.1.69.2</address>

<address >127.0.0.1</address>

</ip>
<ip n="40" >
<address >40.1.25.2</address>

<address >40.1.63.2</address>

<address >40.1.69.2</address>

<address >127.0.0.1</address>

</ip>
<ip n="40" >
<address >40.1.25.2</address>

<address >40.1.63.2</address>

<address >40.1.69.2</address>

<address >127.0.0.1</address>

</ip>
<ip n="41" >
<address >40.1.60.2</address>

<address >40.1.62.2</address>

<address >40.1.68.2</address>

<address >127.0.0.1</address>

</ip>
<ip n="41" >
<address >40.1.60.2</address>

<address >40.1.62.2</address>

<address >40.1.68.2</address>

<address >127.0.0.1</address>

</ip>
<ip n="41" >
<address >40.1.60.2</address>

<address >40.1.62.2</address>

<address >40.1.68.2</address>

<address >127.0.0.1</address>

</ip>
<ip n="41" >
<address >40.1.60.2</address>

<address >40.1.62.2</address>

<address >40.1.68.2</address>

<address >127.0.0.1</address>

</ip>
<ip n="42" >
<address >40.1.45.2</address>

<address >40.1.50.2</address>

<address >40.1.61.2</address>

<address >127.0.0.1</address>

</ip>
<ip n="42" >
<address >40.1.45.2</address>

<address >40.1.50.2</address>

<address >40.1.61.2</address>

<address >127.0.0.1</address>

</ip>
<ip n="42" >
<address >40.1.45.2</address>

<address >40.1.50.2</address>

<address >40.1.61.2</address>

<address >127.0.0.1</address>

</ip>
<ip n="42" >
<address >40.1.45.2</address>

<address >40.1.50.2</address>

<address >40.1.61.2</address>

<address >127.0.0.1</address>

</ip>
<ip n="43" >
<address >40.1.33.2</address>

<address >40.1.49.2</address>

<address >40.1.65.2</address>

<address >127.0.0.1</address>

</ip>
<ip n="43" >
<address >40.1.33.2</address>

<address >40.1.49.2</address>

<address >40.1.65.2</address>

<address >127.0.0.1</address>

</ip>
<ip n="43" >
<address >40.1.33.2</address>

<address >40.1.49.2</address>

<address >40.1.65.2</address>

<address >127.0.0.1</address>

</ip>
<ip n="43" >
<address >40.1.33.2</address>

<address >40.1.49.2</address>

<address >40.1.65.2</address>

<address >127.0.0.1</address>

</ip>
<ip n="44" >
<address >40.1.58.2</address>

<address >40.1.67.2</address>

<address >127.0.0.1</address>

<address >40.1.74.1</address>

</ip>
<ip n="44" >
<address >40.1.58.2</address>

<address >40.1.67.2</address>

<address >127.0.0.1</address>

<address >40.1.74.1</address>

</ip>
<ip n="44" >
<address >40.1.58.2</address>

<address >40.1.67.2</address>

<address >127.0.0.1</address>

<address >40.1.74.1</address>

</ip>
<ip n="44" >
<address >40.1.58.2</address>

<address >40.1.67.2</address>

<address >127.0.0.1</address>

<address >40.1.74.1</address>

</ip>
<ip n="45" >
<address >40.1.7.2</address>

<address >40.1.39.2</address>

<address >127.0.0.1</address>

<address >40.1.75.1</address>

</ip>
<ip n="45" >
<address >40.1.7.2</address>

<address >40.1.39.2</address>

<address >127.0.0.1</address>

<address >40.1.75.1</address>

</ip>
<ip n="45" >
<address >40.1.7.2</address>

<address >40.1.39.2</address>

<address >127.0.0.1</address>

<address >40.1.75.1</address>

</ip>
<ip n="45" >
<address >40.1.7.2</address>

<address >40.1.39.2</address>

<address >127.0.0.1</address>

<address >40.1.75.1</address>

</ip>
<ip n="46" >
<address >40.1.70.2</address>

<address >40.1.73.2</address>

<address >40.1.75.2</address>

<address >127.0.0.1</address>

</ip>
<ip n="46" >
<address >40.1.70.2</address>

<address >40.1.73.2</address>

<address >40.1.75.2</address>

<address >127.0.0.1</address>

</ip>
<ip n="46" >
<address >40.1.70.2</address>

<address >40.1.73.2</address>

<address >40.1.75.2</address>

<address >127.0.0.1</address>

</ip>
<ip n="46" >
<address >40.1.70.2</address>

<address >40.1.73.2</address>

<address >40.1.75.2</address>

<address >127.0.0.1</address>

</ip>
<ip n="47" >
<address >40.1.35.2</address>

<address >40.1.54.2</address>

<address >40.1.74.2</address>

<address >127.0.0.1</address>

</ip>
<ip n="47" >
<address >40.1.35.2</address>

<address >40.1.54.2</address>

<address >40.1.74.2</address>

<address >127.0.0.1</address>

</ip>
<ip n="47" >
<address >40.1.35.2</address>

<address >40.1.54.2</address>

<address >40.1.74.2</address>

<address >127.0.0.1</address>

</ip>
<ip n="47" >
<address >40.1.35.2</address>

<address >40.1.54.2</address>

<address >40.1.74.2</address>

<address >127.0.0.1</address>

</ip>
<ip n="48" >
<address >40.1.56.2</address>

<address >40.1.59.2</address>

<address >40.1.66.2</address>

<address >127.0.0.1</address>

</ip>
<ip n="48" >
<address >40.1.56.2</address>

<address >40.1.59.2</address>

<address >40.1.66.2</address>

<address >127.0.0.1</address>

</ip>
<ip n="48" >
<address >40.1.56.2</address>

<address >40.1.59.2</address>

<address >40.1.66.2</address>

<address >127.0.0.1</address>

</ip>
<ip n="48" >
<address >40.1.56.2</address>

<address >40.1.59.2</address>

<address >40.1.66.2</address>

<address >127.0.0.1</address>

</ip>
<ip n="49" >
<address >40.1.55.2</address>

<address >40.1.57.2</address>

<address >40.1.64.2</address>

<address >127.0.0.1</address>

</ip>
<ip n="49" >
<address >40.1.55.2</address>

<address >40.1.57.2</address>

<address >40.1.64.2</address>

<address >127.0.0.1</address>

</ip>
<ip n="49" >
<address >40.1.55.2</address>

<address >40.1.57.2</address>

<address >40.1.64.2</address>

<address >127.0.0.1</address>

</ip>
<ip n="49" >
<address >40.1.55.2</address>

<address >40.1.57.2</address>

<address >40.1.64.2</address>

<address >127.0.0.1</address>

</ip>
<ipv6 n="0" >
<address >::1</address>

</ipv6>
<ipv6 n="1" >
<address >::1</address>

</ipv6>
<ipv6 n="2" >
<address >::1</address>

</ipv6>
<ipv6 n="3" >
<address >::1</address>

</ipv6>
<ipv6 n="4" >
<address >::1</address>

</ipv6>
<ipv6 n="5" >
<address >::1</address>

</ipv6>
<ipv6 n="6" >
<address >::1</address>

</ipv6>
<ipv6 n="7" >
<address >::1</address>

</ipv6>
<ipv6 n="8" >
<address >::1</address>

</ipv6>
<ipv6 n="9" >
<address >::1</address>

</ipv6>
<ipv6 n="10" >
<address >::1</address>

</ipv6>
<ipv6 n="11" >
<address >::1</address>

</ipv6>
<ipv6 n="12" >
<address >::1</address>

</ipv6>
<ipv6 n="13" >
<address >::1</address>

</ipv6>
<ipv6 n="14" >
<address >::1</address>

</ipv6>
<ipv6 n="15" >
<address >::1</address>

</ipv6>
<ipv6 n="16" >
<address >::1</address>

</ipv6>
<ipv6 n="17" >
<address >::1</address>

</ipv6>
<ipv6 n="18" >
<address >::1</address>

</ipv6>
<ipv6 n="19" >
<address >::1</address>

</ipv6>
<ipv6 n="20" >
<address >::1</address>

</ipv6>
<ipv6 n="21" >
<address >::1</address>

</ipv6>
<ipv6 n="22" >
<address >::1</address>

</ipv6>
<ipv6 n="23" >
<address >::1</address>

</ipv6>
<ipv6 n="24" >
<address >::1</address>

</ipv6>
<ipv6 n="25" >
<address >::1</address>

</ipv6>
<ipv6 n="26" >
<address >::1</address>

</ipv6>
<ipv6 n="27" >
<address >::1</address>

</ipv6>
<ipv6 n="28" >
<address >::1</address>

</ipv6>
<ipv6 n="29" >
<address >::1</address>

</ipv6>
<ipv6 n="30" >
<address >::1</address>

</ipv6>
<ipv6 n="31" >
<address >::1</address>

</ipv6>
<ipv6 n="32" >
<address >::1</address>

</ipv6>
<ipv6 n="33" >
<address >::1</address>

</ipv6>
<ipv6 n="34" >
<address >::1</address>

</ipv6>
<ipv6 n="35" >
<address >::1</address>

</ipv6>
<ipv6 n="36" >
<address >::1</address>

</ipv6>
<ipv6 n="37" >
<address >::1</address>

</ipv6>
<ipv6 n="38" >
<address >::1</address>

</ipv6>
<ipv6 n="39" >
<address >::1</address>

</ipv6>
<ipv6 n="40" >
<address >::1</address>

</ipv6>
<ipv6 n="41" >
<address >::1</address>

</ipv6>
<ipv6 n="42" >
<address >::1</address>

</ipv6>
<ipv6 n="43" >
<address >::1</address>

</ipv6>
<ipv6 n="44" >
<address >::1</address>

</ipv6>
<ipv6 n="45" >
<address >::1</address>

</ipv6>
<ipv6 n="46" >
<address >::1</address>

</ipv6>
<ipv6 n="47" >
<address >::1</address>

</ipv6>
<ipv6 n="48" >
<address >::1</address>

</ipv6>
<ipv6 n="49" >
<address >::1</address>

</ipv6>
<nu p="s" t="0" id="0" w="1" h="1" />
<nu p="s" t="0" id="1" w="1" h="1" />
<nu p="s" t="0" id="2" w="1" h="1" />
<nu p="s" t="0" id="3" w="1" h="1" />
<nu p="s" t="0" id="4" w="1" h="1" />
<nu p="s" t="0" id="5" w="1" h="1" />
<nu p="s" t="0" id="6" w="1" h="1" />
<nu p="s" t="0" id="7" w="1" h="1" />
<nu p="s" t="0" id="8" w="1" h="1" />
<nu p="s" t="0" id="9" w="1" h="1" />
<nu p="s" t="0" id="10" w="1" h="1" />
<nu p="s" t="0" id="11" w="1" h="1" />
<nu p="s" t="0" id="12" w="1" h="1" />
<nu p="s" t="0" id="13" w="1" h="1" />
<nu p="s" t="0" id="14" w="1" h="1" />
<nu p="s" t="0" id="15" w="1" h="1" />
<nu p="s" t="0" id="16" w="1" h="1" />
<nu p="s" t="0" id="17" w="1" h="1" />
<nu p="s" t="0" id="18" w="1" h="1" />
<nu p="s" t="0" id="19" w="1" h="1" />
<nu p="s" t="0" id="20" w="1" h="1" />
<nu p="s" t="0" id="21" w="1" h="1" />
<nu p="s" t="0" id="22" w="1" h="1" />
<nu p="s" t="0" id="23" w="1" h="1" />
<nu p="s" t="0" id="24" w="1" h="1" />
<nu p="s" t="0" id="25" w="1" h="1" />
<nu p="s" t="0" id="26" w="1" h="1" />
<nu p="s" t="0" id="27" w="1" h="1" />
<nu p="s" t="0" id="28" w="1" h="1" />
<nu p="s" t="0" id="29" w="1" h="1" />
<nu p="s" t="0" id="30" w="1" h="1" />
<nu p="s" t="0" id="31" w="1" h="1" />
<nu p="s" t="0" id="32" w="1" h="1" />
<nu p="s" t="0" id="33" w="1" h="1" />
<nu p="s" t="0" id="34" w="1" h="1" />
<nu p="s" t="0" id="35" w="1" h="1" />
<nu p="s" t="0" id="36" w="1" h="1" />
<nu p="s" t="0" id="37" w="1" h="1" />
<nu p="s" t="0" id="38" w="1" h="1" />
<nu p="s" t="0" id="39" w="1" h="1" />
<nu p="s" t="0" id="40" w="1" h="1" />
<nu p="s" t="0" id="41" w="1" h="1" />
<nu p="s" t="0" id="42" w="1" h="1" />
<nu p="s" t="0" id="43" w="1" h="1" />
<nu p="s" t="0" id="44" w="1" h="1" />
<nu p="s" t="0" id="45" w="1" h="1" />
<nu p="s" t="0" id="46" w="1" h="1" />
<nu p="s" t="0" id="47" w="1" h="1" />
<nu p="s" t="0" id="48" w="1" h="1" />
<nu p="s" t="0" id="49" w="1" h="1" />
<ncs ncId="0" n="RemainingEnergy" t="DOUBLE" />
<nu p="d" t="0" id="0" descr="Src" />
<nu p="c" t="0" id="0" r="0" g="0" b="255" />
<nu p="d" t="0" id="9" descr="Sink" />
<nu p="c" t="0" id="9" r="0" g="0" b="255" />
<p fId="0" fbTx="5" lbTx="5.0000864" tId="5" fbRx="5.002422966" lbRx="5.002509366" />
<p fId="0" fbTx="5" lbTx="5.0000864" tId="6" fbRx="5.002422966" lbRx="5.002509366" />
<p fId="0" fbTx="5.0000864" lbTx="5.0001728" tId="5" fbRx="5.002509366" lbRx="5.002595766" />
<p fId="0" fbTx="5.0000864" lbTx="5.0001728" tId="6" fbRx="5.002509366" lbRx="5.002595766" />
<p fId="0" fbTx="5.0001728" lbTx="5.0002592" tId="6" fbRx="5.002595766" lbRx="5.002682166" />
<p fId="5" fbTx="5.002509366" lbTx="5.002602166" tId="35" fbRx="5.004932332" lbRx="5.005025132" />
<p fId="6" fbTx="5.002509366" lbTx="5.002602166" tId="39" fbRx="5.004932332" lbRx="5.005025132" />
<p fId="5" fbTx="5.002595766" lbTx="5.002688566" tId="21" fbRx="5.005018732" lbRx="5.005111532" />
<p fId="6" fbTx="5.002602166" lbTx="5.002694966" tId="39" fbRx="5.005025132" lbRx="5.005117932" />
<p fId="6" fbTx="5.002682166" lbTx="5.002774966" tId="24" fbRx="5.005105132" lbRx="5.005197932" />
<p fId="35" fbTx="5.005025132" lbTx="5.005124332" tId="38" fbRx="5.007448098" lbRx="5.007547298" />
<p fId="39" fbTx="5.005025132" lbTx="5.005124332" tId="46" fbRx="5.007448098" lbRx="5.007547298" />
<p fId="21" fbTx="5.005111532" lbTx="5.005210732" tId="17" fbRx="5.007534498" lbRx="5.007633698" />
<p fId="39" fbTx="5.005117932" lbTx="5.005217132" tId="15" fbRx="5.007540898" lbRx="5.007640098" />
<p fId="24" fbTx="5.005197932" lbTx="5.005297132" tId="48" fbRx="5.007620898" lbRx="5.007720098" />
<p fId="0" fbTx="7" lbTx="7.0000864" tId="6" fbRx="7.002422966" lbRx="7.002509366" />
<p fId="0" fbTx="7" lbTx="7.0000864" tId="36" fbRx="7.002422966" lbRx="7.002509366" />
<p fId="0" fbTx="7" lbTx="7.0000864" tId="5" fbRx="7.002422966" lbRx="7.002509366" />
<p fId="0" fbTx="7.0000864" lbTx="7.0001728" tId="6" fbRx="7.002509366" lbRx="7.002595766" />
<p fId="0" fbTx="7.0000864" lbTx="7.0001728" tId="36" fbRx="7.002509366" lbRx="7.002595766" />
<p fId="6" fbTx="7.002509366" lbTx="7.002602166" tId="24" fbRx="7.004932332" lbRx="7.005025132" />
<p fId="36" fbTx="7.002509366" lbTx="7.002602166" tId="1" fbRx="7.004932332" lbRx="7.005025132" />
<p fId="5" fbTx="7.002509366" lbTx="7.002602166" tId="21" fbRx="7.004932332" lbRx="7.005025132" />
<p fId="36" fbTx="7.002595766" lbTx="7.002688566" tId="8" fbRx="7.005018732" lbRx="7.005111532" />
<p fId="6" fbTx="7.002602166" lbTx="7.002694966" tId="24" fbRx="7.005025132" lbRx="7.005117932" />
<p fId="24" fbTx="7.005025132" lbTx="7.005124332" tId="7" fbRx="7.007448098" lbRx="7.007547298" />
<p fId="1" fbTx="7.005025132" lbTx="7.005124332" tId="28" fbRx="7.007448098" lbRx="7.007547298" />
<p fId="21" fbTx="7.005025132" lbTx="7.005124332" tId="17" fbRx="7.007448098" lbRx="7.007547298" />
<p fId="8" fbTx="7.005111532" lbTx="7.005210732" tId="35" fbRx="7.007534498" lbRx="7.007633698" />
<p fId="24" fbTx="7.005117932" lbTx="7.005217132" tId="48" fbRx="7.007540898" lbRx="7.007640098" />
<p fId="7" fbTx="7.007547298" lbTx="7.007652898" tId="10" fbRx="7.009970264" lbRx="7.010075864" />
<p fId="28" fbTx="7.007547298" lbTx="7.007652898" tId="15" fbRx="7.009970264" lbRx="7.010075864" />
<p fId="17" fbTx="7.007547298" lbTx="7.007652898" tId="13" fbRx="7.009970264" lbRx="7.010075864" />
<p fId="35" fbTx="7.007633698" lbTx="7.007739298" tId="38" fbRx="7.010056664" lbRx="7.010162264" />
<p fId="48" fbTx="7.007640098" lbTx="7.007745698" tId="33" fbRx="7.010063064" lbRx="7.010168664" />
<p fId="10" fbTx="7.010075864" lbTx="7.010187864" tId="27" fbRx="7.01249883" lbRx="7.01261083" />
<p fId="15" fbTx="7.010075864" lbTx="7.010187864" tId="10" fbRx="7.01249883" lbRx="7.01261083" />
<p fId="13" fbTx="7.010075864" lbTx="7.010187864" tId="27" fbRx="7.01249883" lbRx="7.01261083" />
<p fId="38" fbTx="7.010162264" lbTx="7.010274264" tId="34" fbRx="7.01258523" lbRx="7.01269723" />
<p fId="33" fbTx="7.010168664" lbTx="7.010280664" tId="44" fbRx="7.01259163" lbRx="7.01270363" />
<p fId="27" fbTx="7.01261083" lbTx="7.01272923" tId="13" fbRx="7.015033796" lbRx="7.015152196" />
<p fId="10" fbTx="7.01261083" lbTx="7.01272923" tId="7" fbRx="7.015033796" lbRx="7.015152196" />
<p fId="27" fbTx="7.01261083" lbTx="7.01272923" tId="20" fbRx="7.015033796" lbRx="7.015152196" />
<p fId="34" fbTx="7.01269723" lbTx="7.01281563" tId="46" fbRx="7.015120196" lbRx="7.015238596" />
<p fId="44" fbTx="7.01270363" lbTx="7.01282203" tId="47" fbRx="7.015126596" lbRx="7.015244996" />
<p fId="0" fbTx="9" lbTx="9.0000864" tId="5" fbRx="9.002422966" lbRx="9.002509366" />
<p fId="0" fbTx="9" lbTx="9.0000864" tId="6" fbRx="9.002422966" lbRx="9.002509366" />
<p fId="0" fbTx="9" lbTx="9.0000864" tId="36" fbRx="9.002422966" lbRx="9.002509366" />
<p fId="0" fbTx="9.0000864" lbTx="9.0001728" tId="5" fbRx="9.002509366" lbRx="9.002595766" />
<p fId="0" fbTx="9.0001728" lbTx="9.0002592" tId="5" fbRx="9.002595766" lbRx="9.002682166" />
<p fId="5" fbTx="9.002509366" lbTx="9.002602166" tId="21" fbRx="9.004932332" lbRx="9.005025132" />
<p fId="6" fbTx="9.002509366" lbTx="9.002602166" tId="39" fbRx="9.004932332" lbRx="9.005025132" />
<p fId="36" fbTx="9.002509366" lbTx="9.002602166" tId="8" fbRx="9.004932332" lbRx="9.005025132" />
<p fId="5" fbTx="9.002595766" lbTx="9.002688566" tId="35" fbRx="9.005018732" lbRx="9.005111532" />
<p fId="5" fbTx="9.002688566" lbTx="9.002781366" tId="35" fbRx="9.005111532" lbRx="9.005204332" />
<p fId="21" fbTx="9.005025132" lbTx="9.005124332" tId="30" fbRx="9.007448098" lbRx="9.007547298" />
<p fId="39" fbTx="9.005025132" lbTx="9.005124332" tId="46" fbRx="9.007448098" lbRx="9.007547298" />
<p fId="8" fbTx="9.005025132" lbTx="9.005124332" tId="40" fbRx="9.007448098" lbRx="9.007547298" />
<p fId="35" fbTx="9.005111532" lbTx="9.005210732" tId="8" fbRx="9.007534498" lbRx="9.007633698" />
<p fId="35" fbTx="9.005204332" lbTx="9.005303532" tId="38" fbRx="9.007627298" lbRx="9.007726498" />
<p fId="30" fbTx="9.007547298" lbTx="9.007652898" tId="2" fbRx="9.009970264" lbRx="9.010075864" />
<p fId="46" fbTx="9.007547298" lbTx="9.007652898" tId="45" fbRx="9.009970264" lbRx="9.010075864" />
<p fId="40" fbTx="9.007547298" lbTx="9.007652898" tId="26" fbRx="9.009970264" lbRx="9.010075864" />
<p fId="8" fbTx="9.007633698" lbTx="9.007739298" tId="36" fbRx="9.010056664" lbRx="9.010162264" />
<p fId="38" fbTx="9.007726498" lbTx="9.007832098" tId="34" fbRx="9.010149464" lbRx="9.010255064" />
<p fId="2" fbTx="9.010075864" lbTx="9.010187864" tId="25" fbRx="9.01249883" lbRx="9.01261083" />
<p fId="45" fbTx="9.010075864" lbTx="9.010187864" tId="2" fbRx="9.01249883" lbRx="9.01261083" />
<p fId="26" fbTx="9.010075864" lbTx="9.010187864" tId="49" fbRx="9.01249883" lbRx="9.01261083" />
<p fId="36" fbTx="9.010162264" lbTx="9.010274264" tId="0" fbRx="9.01258523" lbRx="9.01269723" />
<p fId="34" fbTx="9.010255064" lbTx="9.010367064" tId="40" fbRx="9.01267803" lbRx="9.01279003" />
<p fId="25" fbTx="9.01261083" lbTx="9.01272923" tId="41" fbRx="9.015033796" lbRx="9.015152196" />
<p fId="2" fbTx="9.01261083" lbTx="9.01272923" tId="30" fbRx="9.015033796" lbRx="9.015152196" />
<p fId="49" fbTx="9.01261083" lbTx="9.01272923" tId="23" fbRx="9.015033796" lbRx="9.015152196" />
<p fId="40" fbTx="9.01279003" lbTx="9.01290843" tId="26" fbRx="9.015212996" lbRx="9.015331396" />
<p fId="41" fbTx="9.015152196" lbTx="9.015276996" tId="26" fbRx="9.017575162" lbRx="9.017699962" />
<p fId="30" fbTx="9.015152196" lbTx="9.015276996" tId="7" fbRx="9.017575162" lbRx="9.017699962" />
<p fId="23" fbTx="9.015152196" lbTx="9.015276996" tId="3" fbRx="9.017575162" lbRx="9.017699962" />
<p fId="26" fbTx="9.015331396" lbTx="9.015456196" tId="49" fbRx="9.017754362" lbRx="9.017879162" />
<p fId="26" fbTx="9.017699962" lbTx="9.017831162" tId="40" fbRx="9.020122928" lbRx="9.020254128" />
<p fId="7" fbTx="9.017699962" lbTx="9.017831162" tId="10" fbRx="9.020122928" lbRx="9.020254128" />
<p fId="3" fbTx="9.017699962" lbTx="9.017831162" tId="29" fbRx="9.020122928" lbRx="9.020254128" />
<p fId="49" fbTx="9.017879162" lbTx="9.018010362" tId="22" fbRx="9.020302128" lbRx="9.020433328" />
<p fId="0" fbTx="11" lbTx="11.0000864" tId="5" fbRx="11.00242297" lbRx="11.00250937" />
<p fId="0" fbTx="11" lbTx="11.0000864" tId="6" fbRx="11.00242297" lbRx="11.00250937" />
<p fId="0" fbTx="11" lbTx="11.0000864" tId="36" fbRx="11.00242297" lbRx="11.00250937" />
<p fId="0" fbTx="11.0000864" lbTx="11.0001728" tId="5" fbRx="11.00250937" lbRx="11.00259577" />
<p fId="0" fbTx="11.0001728" lbTx="11.0002592" tId="5" fbRx="11.00259577" lbRx="11.00268217" />
<p fId="5" fbTx="11.00250937" lbTx="11.00260217" tId="35" fbRx="11.00493233" lbRx="11.00502513" />
<p fId="6" fbTx="11.00250937" lbTx="11.00260217" tId="39" fbRx="11.00493233" lbRx="11.00502513" />
<p fId="36" fbTx="11.00250937" lbTx="11.00260217" tId="8" fbRx="11.00493233" lbRx="11.00502513" />
<p fId="5" fbTx="11.00260217" lbTx="11.00269497" tId="35" fbRx="11.00502513" lbRx="11.00511793" />
<p fId="5" fbTx="11.00268217" lbTx="11.00277497" tId="21" fbRx="11.00510513" lbRx="11.00519793" />
<p fId="35" fbTx="11.00502513" lbTx="11.00512433" tId="38" fbRx="11.0074481" lbRx="11.0075473" />
<p fId="39" fbTx="11.00502513" lbTx="11.00512433" tId="15" fbRx="11.0074481" lbRx="11.0075473" />
<p fId="8" fbTx="11.00502513" lbTx="11.00512433" tId="35" fbRx="11.0074481" lbRx="11.0075473" />
<p fId="35" fbTx="11.00511793" lbTx="11.00521713" tId="8" fbRx="11.0075409" lbRx="11.0076401" />
<p fId="21" fbTx="11.00519793" lbTx="11.00529713" tId="17" fbRx="11.0076209" lbRx="11.0077201" />
<p fId="38" fbTx="11.0075473" lbTx="11.0076529" tId="34" fbRx="11.00997026" lbRx="11.01007586" />
<p fId="15" fbTx="11.0075473" lbTx="11.0076529" tId="28" fbRx="11.00997026" lbRx="11.01007586" />
<p fId="35" fbTx="11.0075473" lbTx="11.0076529" tId="5" fbRx="11.00997026" lbRx="11.01007586" />
<p fId="8" fbTx="11.0076401" lbTx="11.0077457" tId="40" fbRx="11.01006306" lbRx="11.01016866" />
<p fId="17" fbTx="11.0077201" lbTx="11.0078257" tId="31" fbRx="11.01014306" lbRx="11.01024866" />
<p fId="34" fbTx="11.01007586" lbTx="11.01018786" tId="40" fbRx="11.01249883" lbRx="11.01261083" />
<p fId="28" fbTx="11.01007586" lbTx="11.01018786" tId="1" fbRx="11.01249883" lbRx="11.01261083" />
<p fId="5" fbTx="11.01007586" lbTx="11.01018786" tId="21" fbRx="11.01249883" lbRx="11.01261083" />
<p fId="40" fbTx="11.01016866" lbTx="11.01028066" tId="34" fbRx="11.01259163" lbRx="11.01270363" />
<p fId="31" fbTx="11.01024866" lbTx="11.01036066" tId="11" fbRx="11.01267163" lbRx="11.01278363" />
<p fId="40" fbTx="11.01261083" lbTx="11.01272923" tId="8" fbRx="11.0150338" lbRx="11.0151522" />
<p fId="1" fbTx="11.01261083" lbTx="11.01272923" tId="19" fbRx="11.0150338" lbRx="11.0151522" />
<p fId="21" fbTx="11.01261083" lbTx="11.01272923" tId="30" fbRx="11.0150338" lbRx="11.0151522" />
<p fId="34" fbTx="11.01270363" lbTx="11.01282203" tId="46" fbRx="11.0151266" lbRx="11.015245" />
<p fId="11" fbTx="11.01278363" lbTx="11.01290203" tId="43" fbRx="11.0152066" lbRx="11.015325" />
<p fId="8" fbTx="11.0151522" lbTx="11.015277" tId="36" fbRx="11.01757516" lbRx="11.01769996" />
<p fId="19" fbTx="11.0151522" lbTx="11.015277" tId="37" fbRx="11.01757516" lbRx="11.01769996" />
<p fId="30" fbTx="11.0151522" lbTx="11.015277" tId="2" fbRx="11.01757516" lbRx="11.01769996" />
<p fId="46" fbTx="11.015245" lbTx="11.0153698" tId="45" fbRx="11.01766796" lbRx="11.01779276" />
<p fId="43" fbTx="11.015325" lbTx="11.0154498" tId="18" fbRx="11.01774796" lbRx="11.01787276" />
<p fId="36" fbTx="11.01769996" lbTx="11.01783116" tId="1" fbRx="11.02012293" lbRx="11.02025413" />
<p fId="37" fbTx="11.01769996" lbTx="11.01783116" tId="13" fbRx="11.02012293" lbRx="11.02025413" />
<p fId="2" fbTx="11.01769996" lbTx="11.01783116" tId="45" fbRx="11.02012293" lbRx="11.02025413" />
<p fId="45" fbTx="11.01779276" lbTx="11.01792396" tId="14" fbRx="11.02021573" lbRx="11.02034693" />
<p fId="18" fbTx="11.01787276" lbTx="11.01800396" tId="38" fbRx="11.02029573" lbRx="11.02042693" />
<p fId="1" fbTx="11.02025413" lbTx="11.02039173" tId="19" fbRx="11.02267709" lbRx="11.02281469" />
<p fId="13" fbTx="11.02025413" lbTx="11.02039173" tId="17" fbRx="11.02267709" lbRx="11.02281469" />
<p fId="45" fbTx="11.02025413" lbTx="11.02039173" tId="46" fbRx="11.02267709" lbRx="11.02281469" />
<p fId="14" fbTx="11.02034693" lbTx="11.02048453" tId="32" fbRx="11.02276989" lbRx="11.02290749" />
<p fId="38" fbTx="11.02042693" lbTx="11.02056453" tId="35" fbRx="11.02284989" lbRx="11.02298749" />
<p fId="19" fbTx="11.02281469" lbTx="11.02295869" tId="42" fbRx="11.02523766" lbRx="11.02538166" />
<p fId="17" fbTx="11.02281469" lbTx="11.02295869" tId="21" fbRx="11.02523766" lbRx="11.02538166" />
<p fId="46" fbTx="11.02281469" lbTx="11.02295869" tId="39" fbRx="11.02523766" lbRx="11.02538166" />
<p fId="32" fbTx="11.02290749" lbTx="11.02305149" tId="9" fbRx="11.02533046" lbRx="11.02547446" />
<p fId="35" fbTx="11.02298749" lbTx="11.02313149" tId="5" fbRx="11.02541046" lbRx="11.02555446" />
<p fId="42" fbTx="11.02538166" lbTx="11.02553206" tId="25" fbRx="11.02780463" lbRx="11.02795503" />
<p fId="21" fbTx="11.02538166" lbTx="11.02553206" tId="30" fbRx="11.02780463" lbRx="11.02795503" />
<p fId="39" fbTx="11.02538166" lbTx="11.02553206" tId="15" fbRx="11.02780463" lbRx="11.02795503" />
<p fId="9" fbTx="11.02547446" lbTx="11.02561206" tId="32" fbRx="11.02789743" lbRx="11.02803503" />
<p fId="32" fbTx="11.02803503" lbTx="11.02816623" tId="14" fbRx="11.03045799" lbRx="11.03058919" />
<p fId="14" fbTx="11.03058919" lbTx="11.03071399" tId="45" fbRx="11.03301216" lbRx="11.03313696" />
<p fId="45" fbTx="11.03313696" lbTx="11.03325536" tId="46" fbRx="11.03555992" lbRx="11.03567832" />
<p fId="46" fbTx="11.03567832" lbTx="11.03579032" tId="34" fbRx="11.03810129" lbRx="11.03821329" />
<p fId="34" fbTx="11.03821329" lbTx="11.03831889" tId="40" fbRx="11.04063626" lbRx="11.04074186" />
<p fId="40" fbTx="11.04074186" lbTx="11.04084106" tId="8" fbRx="11.04316482" lbRx="11.04326402" />
<p fId="8" fbTx="11.04326402" lbTx="11.04335682" tId="35" fbRx="11.04568699" lbRx="11.04577979" />
<p fId="35" fbTx="11.04577979" lbTx="11.04586619" tId="5" fbRx="11.04820275" lbRx="11.04828915" />
<p fId="5" fbTx="11.04828915" lbTx="11.04836915" tId="0" fbRx="11.05071212" lbRx="11.05079212" />
</anim>
